README.md
requirements.txt
setup.py
pt_lambda_wrapper.egg-info/PKG-INFO
pt_lambda_wrapper.egg-info/SOURCES.txt
pt_lambda_wrapper.egg-info/dependency_links.txt
pt_lambda_wrapper.egg-info/requires.txt
pt_lambda_wrapper.egg-info/top_level.txt
src/__init__.py
src/eventWrapper.py
src/httpWrapper.py
src/queueWrapper.py