Metadata-Version: 1.0
Name: pt-lambda-wrapper
Version: 0.1.9
Summary: trigger wrapper for aws lambda application
Home-page: UNKNOWN
Author: JimmyMo
Author-email: jocund_mo@aliyun.com
License: Apache License 2.0
Platform: UNKNOWN
